emmontopy-0.8.1.data/data/share/EMMOntoPy/LICENSE.txt
emmontopy-0.8.1.data/data/share/EMMOntoPy/README.md
emmontopy-0.8.1.data/data/share/EMMOntoPy/demo/Al-Fe4Al13.cif
emmontopy-0.8.1.data/data/share/EMMOntoPy/demo/README.md
emmontopy-0.8.1.data/data/share/EMMOntoPy/demo/atoms.json
emmontopy-0.8.1.data/data/share/EMMOntoPy/demo/define_ontology.py
emmontopy-0.8.1.data/data/share/EMMOntoPy/demo/emmo2meta.py
emmontopy-0.8.1.data/data/share/EMMOntoPy/demo/materials.svg
emmontopy-0.8.1.data/data/share/EMMOntoPy/demo/plot_ontology.py
emmontopy-0.8.1.data/data/share/EMMOntoPy/demo/properties+materials.svg
emmontopy-0.8.1.data/data/share/EMMOntoPy/demo/step1_generate_metadata.py
emmontopy-0.8.1.data/data/share/EMMOntoPy/demo/step2_define_metadata.py
emmontopy-0.8.1.data/data/share/EMMOntoPy/demo/step3_instantiate.py
emmontopy-0.8.1.data/data/share/EMMOntoPy/demo/step4_map_instance.py
emmontopy-0.8.1.data/data/share/EMMOntoPy/demo/types+properties.svg
emmontopy-0.8.1.data/data/share/EMMOntoPy/demo/units+properties.svg
emmontopy-0.8.1.data/data/share/EMMOntoPy/demo/usercase_ontology-parents.svg
emmontopy-0.8.1.data/data/share/EMMOntoPy/demo/usercase_ontology.owl
emmontopy-0.8.1.data/data/share/EMMOntoPy/demo/usercase_ontology.svg
emmontopy-0.8.1.data/data/share/EMMOntoPy/examples/emmodoc/README.md
emmontopy-0.8.1.data/data/share/EMMOntoPy/examples/emmodoc/classes.md
emmontopy-0.8.1.data/data/share/EMMOntoPy/examples/emmodoc/emmo.md
emmontopy-0.8.1.data/data/share/EMMOntoPy/examples/emmodoc/emmodoc-meta.yaml
emmontopy-0.8.1.data/data/share/EMMOntoPy/examples/emmodoc/important_concepts.md
emmontopy-0.8.1.data/data/share/EMMOntoPy/examples/emmodoc/introduction.md
emmontopy-0.8.1.data/data/share/EMMOntoPy/examples/emmodoc/pandoc-html-options.yaml
emmontopy-0.8.1.data/data/share/EMMOntoPy/examples/emmodoc/pandoc-html.css
emmontopy-0.8.1.data/data/share/EMMOntoPy/examples/emmodoc/pandoc-options.yaml
emmontopy-0.8.1.data/data/share/EMMOntoPy/examples/emmodoc/pandoc-pdf-options.yaml
emmontopy-0.8.1.dist-info/licenses/LICENSE.txt
emmontopy-0.8.1.dist-info/METADATA
emmontopy-0.8.1.dist-info/WHEEL
emmontopy-0.8.1.dist-info/top_level.txt
emmontopy-0.8.1.dist-info/RECORD
