Metadata-Version: 2.4
Name: EMMOntoPy
Version: 0.8.1
Summary: Python reference API for the Elementary MultiperspectiveMaterial Ontology.
Home-page: https://github.com/emmo-repo/EMMOntoPy
Author: Jesper Friis, Francesca Lønstad Bleken, Casper Welzel Andersen, Bjørn Tore Løvfall
Author-email: jesper.friis@sintef.no
License: BSD
Classifier: Development Status :: 2 - Pre-Alpha
Classifier: Intended Audience :: Developers
Classifier: Intended Audience :: Information Technology
Classifier: Intended Audience :: Science/Research
Classifier: License :: OSI Approved :: BSD License
Classifier: Operating System :: OS Independent
Classifier: Programming Language :: Python :: 3
Classifier: Programming Language :: Python :: 3.9
Classifier: Programming Language :: Python :: 3.10
Classifier: Programming Language :: Python :: 3.11
Classifier: Programming Language :: Python :: 3.12
Classifier: Programming Language :: Python :: 3.13
Classifier: Topic :: Scientific/Engineering
Classifier: Topic :: Scientific/Engineering :: Information Analysis
Classifier: Topic :: Scientific/Engineering :: Visualization
Classifier: Topic :: Software Development :: Documentation
Classifier: Topic :: Software Development :: Libraries :: Python Modules
Requires-Python: >=3.7
License-File: LICENSE.txt
Requires-Dist: blessings<2,>=1.7
Requires-Dist: Cython<3.1,>=0.29.21
Requires-Dist: defusedxml<1,>=0.7.1
Requires-Dist: graphviz<0.21,>=0.16
Requires-Dist: numpy<3,>=1.19.5
Requires-Dist: openpyxl<3.2,>=3.0.9
Requires-Dist: Owlready2!=0.32,!=0.34,<0.48,>=0.28
Requires-Dist: packaging<26,>=21.0
Requires-Dist: pandas<2.3,>=1.2
Requires-Dist: Pygments<3,>=2.7.4
Requires-Dist: pyparsing>=2.4.7
Requires-Dist: PyYAML<7,>=5.4.1
Requires-Dist: rdflib<8,>=4.2.1
Requires-Dist: requests<3,>=2.31
Requires-Dist: semver<4,>=2.8.1
Provides-Extra: dev
Requires-Dist: pre-commit~=4.2; python_version >= "3.9" and extra == "dev"
Requires-Dist: pylint~=3.3; python_version >= "3.9" and extra == "dev"
Requires-Dist: pytest~=8.3; python_version >= "3.9" and extra == "dev"
Requires-Dist: pytest-cov~=6.1; python_version >= "3.9" and extra == "dev"
Requires-Dist: mike~=2.1; extra == "dev"
Requires-Dist: mkdocs~=1.6; python_version >= "3.9" and extra == "dev"
Requires-Dist: mkdocs-awesome-pages-plugin~=2.9; extra == "dev"
Requires-Dist: mkdocs-material~=9.6; python_version >= "3.9" and extra == "dev"
Requires-Dist: mkdocstrings[python-legacy]~=0.26.2; python_version >= "3.9" and extra == "dev"
Provides-Extra: docs
Requires-Dist: mike~=2.1; extra == "docs"
Requires-Dist: mkdocs~=1.6; python_version >= "3.9" and extra == "docs"
Requires-Dist: mkdocs-awesome-pages-plugin~=2.9; extra == "docs"
Requires-Dist: mkdocs-material~=9.6; python_version >= "3.9" and extra == "docs"
Requires-Dist: mkdocstrings[python-legacy]~=0.26.2; python_version >= "3.9" and extra == "docs"
Dynamic: author
Dynamic: author-email
Dynamic: classifier
Dynamic: description
Dynamic: description-content-type
Dynamic: home-page
Dynamic: license
Dynamic: license-file
Dynamic: provides-extra
Dynamic: requires-dist
Dynamic: requires-python
Dynamic: summary
